django_google_integrations/__init__.py
django_google_integrations/apis.py
django_google_integrations/exceptions.py
django_google_integrations/models.py
django_google_integrations/serializers.py
django_google_integrations/services.py
django_google_integrations/settings.py
django_google_integrations/utils.py
django_google_integrations/migrations/0001_initial.py
django_google_integrations/migrations/__init__.py
django_google_integrations-0.0.3.dist-info/LICENSE
django_google_integrations-0.0.3.dist-info/METADATA
django_google_integrations-0.0.3.dist-info/WHEEL
django_google_integrations-0.0.3.dist-info/top_level.txt
django_google_integrations-0.0.3.dist-info/RECORD
