Metadata-Version: 2.1
Name: django-google-integrations
Version: 0.0.3
Summary: Integrate Google OAuth in your Django Rest-framework project
Home-page: https://github.com/PrimedigitalGlobal/django-google-integration
Author: Primedigital Global
Author-email: backend@primedigital.tech
License: MIT License
Keywords: django rest_framework google signin
Classifier: Development Status :: 3 - Alpha
Classifier: Framework :: Django
Classifier: Framework :: Django :: 2.2
Classifier: Framework :: Django :: 3.0
Classifier: Framework :: Django :: 3.1
Classifier: Framework :: Django :: 3.2
Classifier: Framework :: Django :: 4.0
Classifier: Intended Audience :: Developers
Classifier: License :: OSI Approved :: BSD License
Classifier: Natural Language :: English
Classifier: Programming Language :: Python :: 3
Classifier: Programming Language :: Python :: 3.5
Classifier: Programming Language :: Python :: 3.6
Classifier: Programming Language :: Python :: 3.7
Classifier: Programming Language :: Python :: 3.8
Classifier: Programming Language :: Python :: 3.9
License-File: LICENSE
Requires-Dist: google-api-python-client (>2.8.0)
Requires-Dist: google-auth-httplib2 (>=0.0.4)
Requires-Dist: google-auth-oauthlib (>0.4.0)
